pardoc/__init__.py
pardoc/default.py
pardoc/google.py
pardoc/liquidpy.py
pardoc/numpy.py
pardoc/parsed.py
pardoc-0.2.0.dist-info/LICENSE
pardoc-0.2.0.dist-info/METADATA
pardoc-0.2.0.dist-info/WHEEL
pardoc-0.2.0.dist-info/RECORD
